pywasm/__init__.py
pywasm/__main__.py
pywasm/arith.py
pywasm/core.py
pywasm/leb128.py
pywasm/log.py
pywasm/opcode.py
pywasm/wasi.py
pywasm-2.2.1.dist-info/METADATA
pywasm-2.2.1.dist-info/WHEEL
pywasm-2.2.1.dist-info/licenses/LICENSE
pywasm-2.2.1.dist-info/RECORD
