Metadata-Version: 2.4
Name: pywasm
Version: 2.2.1
Summary: WebAssembly Interpreter by pure Python
Project-URL: homepage, https://github.com/mohanson/pywasm
Author-email: Mohanson <mohanson@outlook.com>
License: MIT License
License-File: LICENSE
